LICENSE
MANIFEST.in
README.md
requirements.txt
setup.py
hsuBug/__init__.py
hsuBug/bug.py
hsuBug/functions.py
hsuBug.egg-info/PKG-INFO
hsuBug.egg-info/SOURCES.txt
hsuBug.egg-info/dependency_links.txt
hsuBug.egg-info/requires.txt
hsuBug.egg-info/top_level.txt