Metadata-Version: 2.1
Name: hsuBug
Version: 0.1.5
Summary: BeautifulSoup + requests + tqdm + pandas的一個庫
Home-page: https://github.com/lucashsu95/hsuBug
Download-URL: https://pypi.org/project/hsuBug/
Author: LucasHsu
Author-email: lucashsu95@gmail.com
License: MIT
Classifier: Programming Language :: Python :: 3.7
Classifier: Programming Language :: Python :: 3.8
Classifier: Programming Language :: Python :: 3.9
Classifier: Programming Language :: Python :: 3.10
Classifier: Programming Language :: Python :: 3.11
Requires-Python: >=3.7
License-File: LICENSE
